django_cron/__init__.py
django_cron/admin.py
django_cron/cron.py
django_cron/helpers.py
django_cron/models.py
django_cron/tests.py
django_cron/backends/__init__.py
django_cron/backends/lock/__init__.py
django_cron/backends/lock/base.py
django_cron/backends/lock/cache.py
django_cron/backends/lock/database.py
django_cron/backends/lock/file.py
django_cron/management/__init__.py
django_cron/management/commands/__init__.py
django_cron/management/commands/cronloop.py
django_cron/management/commands/runcrons.py
django_cron/migrations/0001_initial.py
django_cron/migrations/0002_remove_max_length_from_CronJobLog_message.py
django_cron/migrations/0003_cronjoblock.py
django_cron/migrations/__init__.py
django_cron-0.6.0.dist-info/AUTHORS
django_cron-0.6.0.dist-info/LICENSE
django_cron-0.6.0.dist-info/METADATA
django_cron-0.6.0.dist-info/WHEEL
django_cron-0.6.0.dist-info/top_level.txt
django_cron-0.6.0.dist-info/RECORD
